[
  {
    "fullName": "Kevin Castro",
    "birthdate": "1997-03-23",
    "imgUrl": "/src",
    "favSnack": "Chips",
    "giftIdea": "Jeans",
    "dreamDay": "Just a description"
  },
  {
    "fullName": "Kevin Castro",
    "birthdate": "1997-03-23",
    "imgUrl": "/src",
    "favSnack": "Chips",
    "giftIdea": "Jeans",
    "dreamDay": "Just a description"
  },
  {
    "fullName": "Kevin Castro",
    "birthdate": "1997-03-23",
    "imgUrl": "/src",
    "favSnack": "Chips",
    "giftIdea": "Jeans",
    "dreamDay": "Just a description"
  },
  {
    "fullName": "Kevin Castro",
    "birthdate": "1997-03-23",
    "imgUrl": "/src",
    "favSnack": "Chips",
    "giftIdea": "Jeans",
    "dreamDay": "Just a description"
  }
]
